./.dockerignore
./.env.example
./.gitignore
./AUDIT_REPORT.md
./CHANGELOG.md
./CONTRIBUTING.md
./Dockerfile
./LICENSE
./PKG-INFO
./README.md
./SECURITY.md
./analytics.py
./backend_client.py
./chain_indexer.py
./compass_config.example.json
./config.py
./docker-compose.yml
./embedder.py
./gateway.py
./indexer.py
./pyproject.toml
./pytest.ini
./requirements-dev.txt
./requirements.txt
./setup.py
./sync_manager.py
./tool_manifest.py
./ui.py
./.github/workflows/publish.yml
./.github/workflows/test.yml
tool_compass-2.0.1.dist-info/METADATA
tool_compass-2.0.1.dist-info/WHEEL
tool_compass-2.0.1.dist-info/entry_points.txt
tool_compass-2.0.1.dist-info/licenses/LICENSE
tool_compass-2.0.1.dist-info/RECORD
