Metadata-Version: 2.4
Name: tool-compass
Version: 2.0.1
Summary: Semantic MCP tool discovery gateway - find tools by intent, not memory
Project-URL: Homepage, https://github.com/mikeyfrilot/tool-compass
Project-URL: Documentation, https://github.com/mikeyfrilot/tool-compass#readme
Project-URL: Repository, https://github.com/mikeyfrilot/tool-compass.git
Project-URL: Issues, https://github.com/mikeyfrilot/tool-compass/issues
Project-URL: Changelog, https://github.com/mikeyfrilot/tool-compass/blob/main/CHANGELOG.md
Author: Mikey Frilot
License-Expression: MIT
License-File: LICENSE
Keywords: ai,anthropic,claude,hnsw,llm,mcp,model-context-protocol,semantic-search,tool-discovery,vector-search
Classifier: Development Status :: 4 - Beta
Classifier: Intended Audience :: Developers
Classifier: License :: OSI Approved :: MIT License
Classifier: Operating System :: OS Independent
Classifier: Programming Language :: Python :: 3
Classifier: Programming Language :: Python :: 3.10
Classifier: Programming Language :: Python :: 3.11
Classifier: Programming Language :: Python :: 3.12
Classifier: Programming Language :: Python :: 3.13
Classifier: Topic :: Scientific/Engineering :: Artificial Intelligence
Classifier: Topic :: Software Development :: Libraries :: Python Modules
Requires-Python: >=3.10
Requires-Dist: hnswlib<1.0.0,>=0.8.0
Requires-Dist: httpx<1.0.0,>=0.27.0
Requires-Dist: mcp<2.0.0,>=1.0.0
Requires-Dist: numpy<3.0.0,>=1.26.0
Provides-Extra: all
Requires-Dist: gradio<6.0.0,>=5.0.0; extra == 'all'
Requires-Dist: hypothesis>=6.100.0; extra == 'all'
Requires-Dist: pytest-asyncio>=0.23.0; extra == 'all'
Requires-Dist: pytest-cov>=4.1.0; extra == 'all'
Requires-Dist: pytest>=8.0.0; extra == 'all'
Provides-Extra: dev
Requires-Dist: hypothesis>=6.100.0; extra == 'dev'
Requires-Dist: pytest-asyncio>=0.23.0; extra == 'dev'
Requires-Dist: pytest-cov>=4.1.0; extra == 'dev'
Requires-Dist: pytest>=8.0.0; extra == 'dev'
Provides-Extra: ui
Requires-Dist: gradio<6.0.0,>=5.0.0; extra == 'ui'
